littlecolors/__init__.py
littlecolors/color.py
littlecolors/colormap.py
littlecolors/helpers/__init__.py
littlecolors/helpers/show_functions.py
littlecolors/preset/__init__.py
littlecolors/preset/colorlists.py
littlecolors/preset/colormaps.py
littlecolors/preset/colors.py
littlecolors/utils/__init__.py
littlecolors/utils/convertors.py
littlecolors-1.0.1.dist-info/licenses/LICENCE
littlecolors-1.0.1.dist-info/METADATA
littlecolors-1.0.1.dist-info/WHEEL
littlecolors-1.0.1.dist-info/top_level.txt
littlecolors-1.0.1.dist-info/RECORD
