Metadata-Version: 2.4
Name: littlecolors
Version: 1.0.1
Summary: A simple Python package to create, manipulate and mutate colors and color-scales.
Author-email: Matsvei Tsishyn <matsvei.tsishyn@protonmail.com>
License-Expression: MIT
Project-URL: Homepage, https://github.com/MatsveiTsishyn/littlecolors
Classifier: Programming Language :: Python :: 3
Classifier: Operating System :: OS Independent
Requires-Python: >=3.10
License-File: LICENCE
Requires-Dist: numpy
Provides-Extra: helpers
Requires-Dist: matplotlib; extra == "helpers"
Dynamic: license-file
